pysvg/__init__.py
pysvg/animate.py
pysvg/attributes.py
pysvg/builders.py
pysvg/core.py
pysvg/filter.py
pysvg/gradient.py
pysvg/linking.py
pysvg/parser.py
pysvg/script.py
pysvg/shape.py
pysvg/structure.py
pysvg/style.py
pysvg/text.py
pysvg/turtle.py
pysvg/util.py
pysvg_py3-0.2.2.post3.dist-info/LICENSE.md
pysvg_py3-0.2.2.post3.dist-info/METADATA
pysvg_py3-0.2.2.post3.dist-info/WHEEL
pysvg_py3-0.2.2.post3.dist-info/top_level.txt
pysvg_py3-0.2.2.post3.dist-info/RECORD
